[
	{
		"__TYPE__": "SharedSliceContent",
		"variation": "default",
		"primary": {
			"heading": {
				"__TYPE__": "StructuredTextContent",
				"value": [
					{
						"type": "heading1",
						"content": {
							"text": "Running"
						}
					}
				]
			},
			"descr": {
				"__TYPE__": "StructuredTextContent",
				"value": [
					{
						"type": "paragraph",
						"content": {
							"text": "Amet magna id ad. Veniam occaecat anim id amet minim reprehenderit consequat culpa."
						}
					}
				]
			}
		},
		"items": [
			{
				"__TYPE__": "GroupItemContent",
				"value": [
					[
						"category",
						{
							"__TYPE__": "LinkContent",
							"value": {
								"__TYPE__": "DocumentLink",
								"id": "mock_document_id"
							}
						}
					]
				]
			}
		]
	}
]